pytyping/__init__.py
pytyping/app.py
pytyping-0.0.1.dist-info/LICENSE
pytyping-0.0.1.dist-info/METADATA
pytyping-0.0.1.dist-info/WHEEL
pytyping-0.0.1.dist-info/entry_points.txt
pytyping-0.0.1.dist-info/top_level.txt
pytyping-0.0.1.dist-info/RECORD
